mcp_server_w/__init__.py
mcp_server_w/__main__.py
mcp_server_w/server.py
mcp_server_w-0.6.3.dist-info/METADATA
mcp_server_w-0.6.3.dist-info/WHEEL
mcp_server_w-0.6.3.dist-info/entry_points.txt
mcp_server_w-0.6.3.dist-info/RECORD
